platon_keyfile/__init__.py
platon_keyfile/keyfile.py
platon_keyfile-1.2.0.dist-info/LICENSE
platon_keyfile-1.2.0.dist-info/METADATA
platon_keyfile-1.2.0.dist-info/WHEEL
platon_keyfile-1.2.0.dist-info/top_level.txt
platon_keyfile-1.2.0.dist-info/RECORD
