Metadata-Version: 2.1
Name: platon-keyfile
Version: 1.2.0
Summary: A library for handling the encrypted keyfiles used to store platon private keys.
Home-page: https://github.com/platonnetwork/platon-keyfile
Author: Shinnng
Author-email: shinnng@outlook.com
License: MIT
Keywords: platon
Platform: UNKNOWN
Classifier: Development Status :: 2 - Pre-Alpha
Classifier: Intended Audience :: Developers
Classifier: License :: OSI Approved :: MIT License
Classifier: Natural Language :: English
Classifier: Programming Language :: Python :: 3
Classifier: Programming Language :: Python :: 3.4
Classifier: Programming Language :: Python :: 3.5
Classifier: Programming Language :: Python :: 3.6
Classifier: Programming Language :: Python :: 3.7
Classifier: Programming Language :: Python :: 3.8
License-File: LICENSE
Requires-Dist: platon-utils (>=1.2.0)
Requires-Dist: platon-keys (>=1.2.0)
Requires-Dist: pycryptodome (<4,>=3.6.6)
Provides-Extra: dev
Requires-Dist: platon-utils (>=1.2.0) ; extra == 'dev'
Requires-Dist: platon-keys (>=1.2.0) ; extra == 'dev'
Requires-Dist: pycryptodome (<4,>=3.6.6) ; extra == 'dev'
Requires-Dist: bumpversion (<1,>=0.5.3) ; extra == 'dev'
Requires-Dist: wheel ; extra == 'dev'
Requires-Dist: setuptools (>=36.2.0) ; extra == 'dev'
Requires-Dist: pluggy (==0.7.1) ; extra == 'dev'
Requires-Dist: idna (==2.7) ; extra == 'dev'
Requires-Dist: requests (<3,>=2.20) ; extra == 'dev'
Requires-Dist: tox (>=2.7.0) ; extra == 'dev'
Requires-Dist: twine ; extra == 'dev'
Requires-Dist: pytest (<3.7,>=3.6) ; extra == 'dev'
Requires-Dist: flake8 (==3.5.0) ; extra == 'dev'
Provides-Extra: keyfile
Requires-Dist: platon-utils (>=1.2.0) ; extra == 'keyfile'
Requires-Dist: platon-keys (>=1.2.0) ; extra == 'keyfile'
Requires-Dist: pycryptodome (<4,>=3.6.6) ; extra == 'keyfile'
Provides-Extra: lint
Requires-Dist: flake8 (==3.5.0) ; extra == 'lint'
Provides-Extra: test
Requires-Dist: pytest (<3.7,>=3.6) ; extra == 'test'
